LICENSE
MANIFEST.in
README.rst
setup.py
django_protractor.egg-info/PKG-INFO
django_protractor.egg-info/SOURCES.txt
django_protractor.egg-info/dependency_links.txt
django_protractor.egg-info/requires.txt
django_protractor.egg-info/top_level.txt
protractor/__init__.py
protractor/models.py
protractor/test.py
protractor/management/__init__.py
protractor/management/commands/__init__.py
protractor/management/commands/protractor.py