Metadata-Version: 1.1
Name: django-protractor
Version: 0.4
Summary: Easily integrate your protractor tests with django
Home-page: UNKNOWN
Author: James Pulec
Author-email: jpulec@gmail.com
License: MIT License
Platform: UNKNOWN
Classifier: Environment :: Web Environment
Classifier: Framework :: Django
Classifier: Intended Audience :: Developers
Classifier: Operating System :: OS Independent
Classifier: Programming Language :: Python
Classifier: Programming Language :: Python :: 2
Classifier: Programming Language :: Python :: 3
